Metadata-Version: 2.1
Name: canivete
Version: 0.1
Summary: bla bla bla
Home-page: https://github.com/joilsouza/canivete
Author: joilsouza
Author-email: joilsouza@hotmail.com
License: MIT
Platform: UNKNOWN
